reportsector/__init__.py
reportsector/cli.py
reportsector/main.py
reportsector/utils.py
reportsector/templates/aggregate.sh.j2
reportsector/templates/bash.sh.j2
reportsector/templates/buildkit.sh.j2
reportsector/templates/containerd.sh.j2
reportsector/templates/kubeadm-init.sh.j2
reportsector/templates/kubectl.sh.j2
reportsector/templates/nerdctl.sh.j2
reportsector/templates/runc.sh.j2
reportsector/templates/yj.sh.j2
reportsector/templates/yq.sh.j2
reportsector-0.0.8.dist-info/LICENSE.txt
reportsector-0.0.8.dist-info/METADATA
reportsector-0.0.8.dist-info/WHEEL
reportsector-0.0.8.dist-info/entry_points.txt
reportsector-0.0.8.dist-info/top_level.txt
reportsector-0.0.8.dist-info/RECORD
